README
setup.py
hxsd/__init__.py
hxsd.egg-info/PKG-INFO
hxsd.egg-info/SOURCES.txt
hxsd.egg-info/dependency_links.txt
hxsd.egg-info/entry_points.txt
hxsd.egg-info/top_level.txt