Metadata-Version: 1.0
Name: hxsd
Version: 0.1.0
Summary: Simple Service discovering library
Home-page: https://github.com/rossdylan/Helixode-SD
Author: Ross Delinger
Author-email: rossdylan@csh.rit.edu
License: UNKNOWN
Platform: UNKNOWN
